quickv.cpython-313-x86_64-linux-gnu.so
quickv-0.1.8.dist-info/METADATA
quickv-0.1.8.dist-info/WHEEL
quickv-0.1.8.dist-info/top_level.txt
quickv-0.1.8.dist-info/RECORD
