Metadata-Version: 2.4
Name: quickv
Version: 0.1.8
Summary: QuicKV is a fast, embedded key-value store database, built for Python, with no dependencies. 
Home-page: https://github.com/dragonpeti53/quickv
Author: Your Name
Author-email: you@example.com
Classifier: Programming Language :: Python :: 3
Classifier: Programming Language :: C
Classifier: Operating System :: OS Independent
Requires-Python: >=3.6
Dynamic: author
Dynamic: author-email
Dynamic: classifier
Dynamic: home-page
Dynamic: requires-python
Dynamic: summary
